README.md
setup.py
leetcode/__init__.py
leetcode/api_client.py
leetcode/configuration.py
leetcode/rest.py
leetcode/api/__init__.py
leetcode/api/default_api.py
leetcode/models/__init__.py
leetcode/models/base_submission_result.py
leetcode/models/difficulty.py
leetcode/models/graphql_data.py
leetcode/models/graphql_query.py
leetcode/models/graphql_query_variables.py
leetcode/models/graphql_question_code_snippet.py
leetcode/models/graphql_question_contributor.py
leetcode/models/graphql_question_detail.py
leetcode/models/graphql_question_solution.py
leetcode/models/graphql_question_topic_tag.py
leetcode/models/graphql_response.py
leetcode/models/graphql_user.py
leetcode/models/id.py
leetcode/models/inline_response200.py
leetcode/models/interpretation.py
leetcode/models/one_ofid.py
leetcode/models/one_ofinline_response200.py
leetcode/models/problems.py
leetcode/models/stat.py
leetcode/models/stat_status_pair.py
leetcode/models/submission.py
leetcode/models/submission_id.py
leetcode/models/submission_result.py
leetcode/models/test_submission.py
leetcode/models/test_submission_result.py
pyleetcode_api.egg-info/PKG-INFO
pyleetcode_api.egg-info/SOURCES.txt
pyleetcode_api.egg-info/dependency_links.txt
pyleetcode_api.egg-info/requires.txt
pyleetcode_api.egg-info/top_level.txt
test/__init__.py
test/test_base_submission_result.py
test/test_default_api.py
test/test_difficulty.py
test/test_graphql_data.py
test/test_graphql_query.py
test/test_graphql_query_variables.py
test/test_graphql_question_code_snippet.py
test/test_graphql_question_contributor.py
test/test_graphql_question_detail.py
test/test_graphql_question_solution.py
test/test_graphql_question_topic_tag.py
test/test_graphql_response.py
test/test_graphql_user.py
test/test_id.py
test/test_inline_response200.py
test/test_interpretation.py
test/test_one_ofid.py
test/test_one_ofinline_response200.py
test/test_problems.py
test/test_stat.py
test/test_stat_status_pair.py
test/test_submission.py
test/test_submission_id.py
test/test_submission_result.py
test/test_test_submission.py
test/test_test_submission_result.py